{
  "source": "./site",
  "destination": "./out/site",
  "excludes": ["Publisher/Builder/template/", "BuiltinExternal/"],
  "title": "ESDoc",
  "styles": ["./site/css/style.css"],
  "scripts": ["./site/js/analytics.js", "./site/js/inner-link.js"],
  "plugins": [{"name": "./site/plugin/site-plugin.js"}],
  "manual": {
    "globalIndex": true,
    "asset": "./site/manual/asset",
    "index": "./site/manual/index.md",
    "overview": [],
    "design": [],
    "installation": [],
    "usage": ["./site/manual/usage/usage.md", "./site/manual/usage/feature.md", "./site/manual/usage/tags.md"],
    "tutorial": [],
    "configuration": ["./site/manual/configuration/config.md"],
    "example": [],
    "advanced": ["./site/manual/advanced/api.md"],
    "faq": ["./site/manual/faq/faq.md"],
    "changelog": ["./CHANGELOG.md"]
  }
}
